warpcoder/__init__.py
warpcoder/__main__.py
warpcoder/main.py
warpcoder/prompts.yaml
warpcoder/starship1.py
warpcoder/starship2.py
warpcoder/starship_base.py
warpcoder/assets/CLAUDE.md
warpcoder/assets/.claude/settings.json
warpcoder/assets/.claude/settings.local.json
warpcoder/assets/.claude/ai_docs/claude_code_fresh_tutorials.md
warpcoder/assets/.claude/commands/bddinit.md
warpcoder/assets/.claude/commands/bddwarp.md
warpcoder/assets/.claude/commands/prime.md
warpcoder/assets/.claude/commands/ssa-lab.md
warpcoder/assets/.claude/commands/ssa-scan.md
warpcoder/assets/.claude/example_specs/specs_html_javascript_ui/invent_new_ui.md
warpcoder/assets/.claude/example_specs/specs_html_javascript_ui/invent_new_ui_v2.md
warpcoder/assets/.claude/example_specs/specs_html_javascript_ui/invent_new_ui_v3.md
warpcoder/assets/.claude/example_specs/specs_html_javascript_ui/invent_new_ui_v4.md
warpcoder/assets/.claude/example_specs/specs_python_pyqt6_ui/create_pyqt6_app_v1.md
warpcoder-0.4.4.dist-info/licenses/LICENSE.txt
warpcoder-0.4.4.dist-info/licenses/LICENSE_HEADER.txt
warpcoder-0.4.4.dist-info/METADATA
warpcoder-0.4.4.dist-info/WHEEL
warpcoder-0.4.4.dist-info/entry_points.txt
warpcoder-0.4.4.dist-info/top_level.txt
warpcoder-0.4.4.dist-info/RECORD
