Metadata-Version: 2.4
Name: warpcoder
Version: 0.4.4
Summary: Universal BDD Project Generator for Claude Code
Author-email: Warpcoders LLC <starshipagentic@gmail.com>
License: Proprietary
Project-URL: Homepage, https://github.com/starshipagentic/warpcoder
Project-URL: Repository, https://github.com/starshipagentic/warpcoder
Project-URL: Issues, https://github.com/starshipagentic/warpcoder/issues
Keywords: bdd,claude,testing,development,automation
Classifier: Development Status :: 4 - Beta
Classifier: Environment :: Console
Classifier: Intended Audience :: Developers
Classifier: License :: Other/Proprietary License
Classifier: Operating System :: OS Independent
Classifier: Programming Language :: Python :: 3
Classifier: Programming Language :: Python :: 3.8
Classifier: Programming Language :: Python :: 3.9
Classifier: Programming Language :: Python :: 3.10
Classifier: Programming Language :: Python :: 3.11
Classifier: Programming Language :: Python :: 3.12
Classifier: Topic :: Software Development :: Testing
Classifier: Topic :: Software Development :: Code Generators
Requires-Python: >=3.8
License-File: LICENSE.txt
License-File: LICENSE_HEADER.txt
Requires-Dist: questionary>=2.0.0
Requires-Dist: rich>=13.0.0
Requires-Dist: pyyaml>=6.0.0
Provides-Extra: dev
Requires-Dist: pytest>=7.0; extra == "dev"
Requires-Dist: black>=23.0; extra == "dev"
Requires-Dist: ruff>=0.1.0; extra == "dev"
Requires-Dist: build>=0.10.0; extra == "dev"
Requires-Dist: twine>=4.0.0; extra == "dev"
Dynamic: license-file
